django_model_history_tracker/__init__.py
django_model_history_tracker/admin.py
django_model_history_tracker/mixins.py
django_model_history_tracker/models.py
tests/__init__.py
tests/test_history_tracker.py
django_model_history_tracker-0.2.dist-info/LICENSE
django_model_history_tracker-0.2.dist-info/METADATA
django_model_history_tracker-0.2.dist-info/WHEEL
django_model_history_tracker-0.2.dist-info/top_level.txt
django_model_history_tracker-0.2.dist-info/RECORD
