Metadata-Version: 2.1
Name: django-model-history-tracker
Version: 0.2
Summary: A Django utility to track changes to model instances and save the history of updates.
Home-page: https://github.com/yourusername/django_model_history_tracker
Author: Your Name
Author-email: your.email@example.com
License: MIT License
Keywords: django model history tracker auditing
Classifier: Development Status :: 3 - Alpha
Classifier: License :: OSI Approved :: MIT License
Classifier: Intended Audience :: Developers
Classifier: Framework :: Django
Classifier: Programming Language :: Python :: 3
Classifier: Programming Language :: Python :: 3.6
Classifier: Programming Language :: Python :: 3.7
Classifier: Programming Language :: Python :: 3.8
Classifier: Programming Language :: Python :: 3.9
License-File: LICENSE
Requires-Dist: Django (>=2.2)
